winHidder.exe
winHidder.py
winhidder-0.1.1.dist-info/entry_points.txt
winhidder-0.1.1.dist-info/METADATA
winhidder-0.1.1.dist-info/WHEEL
winhidder-0.1.1.dist-info/RECORD
