Metadata-Version: 2.1
Name: winhidder
Version: 0.1.1
Summary: switch desktop with mouse on windows
License: MIT
Author: Your Name
Author-email: you@example.com
Requires-Python: >=3.10,<4.0
Classifier: License :: OSI Approved :: MIT License
Classifier: Programming Language :: Python :: 3
Classifier: Programming Language :: Python :: 3.10
Classifier: Programming Language :: Python :: 3.11
